AUTHORS
CHANGELOG.txt
DESCRIPTION
LICENSE
MANIFEST.in
README.rst
setup.cfg
setup.py
djangocms_text_redactor/__init__.py
djangocms_text_redactor/cms_plugins.py
djangocms_text_redactor/models.py
djangocms_text_redactor/urls.py
djangocms_text_redactor/views.py
djangocms_text_redactor.egg-info/PKG-INFO
djangocms_text_redactor.egg-info/SOURCES.txt
djangocms_text_redactor.egg-info/dependency_links.txt
djangocms_text_redactor.egg-info/requires.txt
djangocms_text_redactor.egg-info/top_level.txt
djangocms_text_redactor/migrations/0001_initial.py
djangocms_text_redactor/migrations/0002_auto__add_field_redactortext_redactor_settings.py
djangocms_text_redactor/migrations/__init__.py
djangocms_text_redactor/templates/djangocms_text_redactor/.empty
djangocms_text_redactor/templates/djangocms_text_redactor/redactor_plugin.html
djangocms_text_redactor/tests/.coverage
djangocms_text_redactor/tests/.coveragerc
djangocms_text_redactor/tests/__init__.py
djangocms_text_redactor/tests/factories.py
djangocms_text_redactor/tests/models_tests.py
djangocms_text_redactor/tests/runtests.py
djangocms_text_redactor/tests/south_settings.py
djangocms_text_redactor/tests/test_settings.py
djangocms_text_redactor/tests/urls.py
djangocms_text_redactor/tests/views_tests.py
djangocms_text_redactor/tests/test_app/__init__.py
djangocms_text_redactor/tests/test_app/models.py
djangocms_text_redactor/tests/test_app/templates/400.html
djangocms_text_redactor/tests/test_app/templates/500.html
djangocms_text_redactor/tests/test_app/templates/base.html
djangocms_text_redactor/tests/test_app/templates/default.html