Metadata-Version: 1.0
Name: djangocms-text-redactor
Version: 0.1.1
Summary: A django-cms plugin that displays text and uses the redactor editor for editing.
